forust-0.4.8.dist-info/METADATA
forust-0.4.8.dist-info/WHEEL
forust-0.4.8.dist-info/license_files/LICENSE
forust/__init__.py
forust/serialize.py
forust/forust.cpython-312-x86_64-linux-gnu.so
forust-0.4.8.dist-info/RECORD
