Metadata-Version: 2.3
Name: forust
Version: 0.4.8
Classifier: Programming Language :: Rust
Classifier: Programming Language :: Python :: Implementation :: CPython
Classifier: Programming Language :: Python :: Implementation :: PyPy
Requires-Dist: numpy >=1.21
Requires-Dist: pandas >=1.3
Requires-Dist: maturin ; extra == 'dev'
Requires-Dist: pytest ; extra == 'dev'
Requires-Dist: seaborn ; extra == 'dev'
Requires-Dist: xgboost ==1.6.1 ; extra == 'dev'
Requires-Dist: scikit-learn ; extra == 'dev'
Requires-Dist: mkdocs-material ==9.* ; extra == 'dev'
Requires-Dist: mkdocstrings[python] ==0.22.0 ; extra == 'dev'
Requires-Dist: mkdocs-autorefs ; extra == 'dev'
Requires-Dist: ruff >=0.0.272 ; extra == 'dev'
Provides-Extra: dev
License-File: LICENSE
Summary: A lightweight gradient boosting implementation in Rust.
Keywords: rust,forust,machine learning,xgboost,tree model,decision tree
Author: James Inlow
Requires-Python: >=3.8
